LICENSE
MANIFEST.in
README.rst
setup.py
nnkit/__init__.py
nnkit/activation.py
nnkit/arithmetic.py
nnkit/initialization.py
nnkit/loss.py
nnkit/normalization.py
nnkit/optimization.py
nnkit/regularization.py
nnkit/serialization.py
nnkit.egg-info/PKG-INFO
nnkit.egg-info/SOURCES.txt
nnkit.egg-info/dependency_links.txt
nnkit.egg-info/not-zip-safe
nnkit.egg-info/requires.txt
nnkit.egg-info/top_level.txt