Metadata-Version: 1.0
Name: nnkit
Version: 1.4.0
Summary: NNKit: A Python framework for creating dynamic neural networks.
Home-page: http://github.com/saldavonschwartz/nnkit.git
Author: Federico Saldarini
Author-email: fede@0xfede.io
License: MIT
Keywords: neural networks ai AI
Platform: UNKNOWN
